{
	"configurations" : 
	[
		{
			"directories" : 
			[
				{
					"build" : ".",
					"childIndexes" : 
					[
						1,
						2,
						3,
						4
					],
					"jsonFile" : "directory-.-Debug-d0094a50bb2071803777.json",
					"minimumCMakeVersion" : 
					{
						"string" : "3.12.0"
					},
					"projectIndex" : 0,
					"source" : "."
				},
				{
					"build" : "DirectXTex",
					"jsonFile" : "directory-DirectXTex-Debug-41be9049bbd5ee0511e9.json",
					"minimumCMakeVersion" : 
					{
						"string" : "3.12.3"
					},
					"parentIndex" : 0,
					"projectIndex" : 0,
					"source" : "DirectXTex",
					"targetIndexes" : 
					[
						0
					]
				},
				{
					"build" : "Engine",
					"jsonFile" : "directory-Engine-Debug-e7cda9100e735d363573.json",
					"minimumCMakeVersion" : 
					{
						"string" : "3.12.1"
					},
					"parentIndex" : 0,
					"projectIndex" : 0,
					"source" : "Engine",
					"targetIndexes" : 
					[
						1,
						2,
						5
					]
				},
				{
					"build" : "Tutorial4",
					"jsonFile" : "directory-Tutorial4-Debug-f0023c8cfe58d2913d80.json",
					"minimumCMakeVersion" : 
					{
						"string" : "3.12.1"
					},
					"parentIndex" : 0,
					"projectIndex" : 0,
					"source" : "Tutorial4",
					"targetIndexes" : 
					[
						4
					]
				},
				{
					"build" : "Sponza",
					"jsonFile" : "directory-Sponza-Debug-c72d6dd42e087976b43e.json",
					"minimumCMakeVersion" : 
					{
						"string" : "3.12.1"
					},
					"parentIndex" : 0,
					"projectIndex" : 0,
					"source" : "Sponza",
					"targetIndexes" : 
					[
						3
					]
				}
			],
			"name" : "Debug",
			"projects" : 
			[
				{
					"directoryIndexes" : 
					[
						0,
						1,
						2,
						3,
						4
					],
					"name" : "Engine3D_DX12",
					"targetIndexes" : 
					[
						0,
						1,
						2,
						3,
						4,
						5
					]
				}
			],
			"targets" : 
			[
				{
					"directoryIndex" : 1,
					"id" : "DirectXTex::@0182fc2a9ab8d5144aec",
					"jsonFile" : "target-DirectXTex-Debug-b2e3367d7876d2022e51.json",
					"name" : "DirectXTex",
					"projectIndex" : 0
				},
				{
					"directoryIndex" : 2,
					"id" : "Engine::@8f69bdd092c897d92c1e",
					"jsonFile" : "target-Engine-Debug-f15f92c019b36927273d.json",
					"name" : "Engine",
					"projectIndex" : 0
				},
				{
					"directoryIndex" : 2,
					"id" : "EngineBin::@8f69bdd092c897d92c1e",
					"jsonFile" : "target-EngineBin-Debug-1ba6918841424749a43b.json",
					"name" : "EngineBin",
					"projectIndex" : 0
				},
				{
					"directoryIndex" : 4,
					"id" : "Sponza::@ba6ce5cf092d61510751",
					"jsonFile" : "target-Sponza-Debug-795ebd183f7e84ac2ceb.json",
					"name" : "Sponza",
					"projectIndex" : 0
				},
				{
					"directoryIndex" : 3,
					"id" : "Tutorial4::@0f2dff933f4eff55eee0",
					"jsonFile" : "target-Tutorial4-Debug-d8699ceb894cdae97bcb.json",
					"name" : "Tutorial4",
					"projectIndex" : 0
				},
				{
					"directoryIndex" : 2,
					"id" : "shaders::@8f69bdd092c897d92c1e",
					"jsonFile" : "target-shaders-Debug-97fbc83040d0f57dde89.json",
					"name" : "shaders",
					"projectIndex" : 0
				}
			]
		}
	],
	"kind" : "codemodel",
	"paths" : 
	{
		"build" : "C:/Users/Ali/Documents/GitHub/Engine3D_DX12/out/build/windows-default",
		"source" : "C:/Users/Ali/Documents/GitHub/Engine3D_DX12"
	},
	"version" : 
	{
		"major" : 2,
		"minor" : 3
	}
}
